exo_messages/__init__.py
exo_messages/admin.py
exo_messages/apps.py
exo_messages/conf.py
exo_messages/exceptions.py
exo_messages/manager.py
exo_messages/models.py
exo_messages/queryset.py
exo_messages/api/__init__.py
exo_messages/api/serializer.py
exo_messages/api/urls.py
exo_messages/api/views.py
exo_messages/migrations/0001_initial.py
exo_messages/migrations/__init__.py
exo_messages/signals/__init__.py
exo_messages/signals/signals_user_logged_handler.py
lib_exo_messages-1.4.1.dist-info/AUTHORS.rst
lib_exo_messages-1.4.1.dist-info/LICENSE
lib_exo_messages-1.4.1.dist-info/METADATA
lib_exo_messages-1.4.1.dist-info/WHEEL
lib_exo_messages-1.4.1.dist-info/top_level.txt
lib_exo_messages-1.4.1.dist-info/RECORD
